beetsplug/xtractor/__init__.py
beetsplug/xtractor/about.py
beetsplug/xtractor/command.py
beetsplug/xtractor/config_default.yml
beetsplug/xtractor/helper.py
beets_xtractor-0.4.2.dist-info/LICENSE.txt
beets_xtractor-0.4.2.dist-info/METADATA
beets_xtractor-0.4.2.dist-info/WHEEL
beets_xtractor-0.4.2.dist-info/top_level.txt
beets_xtractor-0.4.2.dist-info/RECORD
